.mina/satori.toml
avilla/satori/__init__.py
avilla/satori/account.py
avilla/satori/capability.py
avilla/satori/collector/__init__.py
avilla/satori/collector/connection.py
avilla/satori/const.py
avilla/satori/element.py
avilla/satori/event.py
avilla/satori/perform/__init__.py
avilla/satori/perform/action/__init__.py
avilla/satori/perform/action/message.py
avilla/satori/perform/action/request.py
avilla/satori/perform/context.py
avilla/satori/perform/event/__init__.py
avilla/satori/perform/event/activity.py
avilla/satori/perform/event/lifespan.py
avilla/satori/perform/event/message.py
avilla/satori/perform/event/metadata.py
avilla/satori/perform/event/relationship.py
avilla/satori/perform/event/request.py
avilla/satori/perform/message/deserialize.py
avilla/satori/perform/message/serialize.py
avilla/satori/perform/resource_fetch.py
avilla/satori/protocol.py
avilla/satori/resource.py
avilla/satori/service.py
avilla_satori-1.0.0a25.dist-info/METADATA
avilla_satori-1.0.0a25.dist-info/WHEEL
avilla_satori-1.0.0a25.dist-info/licenses/LICENSE
avilla_satori-1.0.0a25.dist-info/RECORD
